odoo/addons/product_code_unique/README.rst
odoo/addons/product_code_unique/__init__.py
odoo/addons/product_code_unique/__manifest__.py
odoo/addons/product_code_unique/hook.py
odoo/addons/product_code_unique/i18n/product_code_unique.pot
odoo/addons/product_code_unique/models/__init__.py
odoo/addons/product_code_unique/models/product.py
odoo/addons/product_code_unique/static/description/icon.png
odoo12_addon_product_code_unique-12.0.1.0.0.dist-info/METADATA
odoo12_addon_product_code_unique-12.0.1.0.0.dist-info/RECORD
odoo12_addon_product_code_unique-12.0.1.0.0.dist-info/WHEEL
odoo12_addon_product_code_unique-12.0.1.0.0.dist-info/top_level.txt
